lodepy/__init__.py
lodepy/setup.py
lodepy/core/__init__.py
lodepy/core/comparable.py
lodepy/core/main.py
lodepy/core/operable.py
lodepy/core/version.py
lodepy/data/__init__.py
lodepy/data/data_store.py
lodepy/data/node_variables.py
lodepy/git/__init__.py
lodepy/git/git_status.py
lodepy/groups/__init__.py
lodepy/groups/group.py
lodepy/groups/group_executor.py
lodepy/groups/group_return.py
lodepy/handling/__init__.py
lodepy/handling/lodepy_error.py
lodepy/handling/log_error.py
lodepy/handling/log_manager.py
lodepy/nodes/__init__.py
lodepy/nodes/node.py
lodepy/nodes/node_executor.py
lodepy/nodes/node_return.py
lodepy/tasks/__init__.py
lodepy/tasks/task.py
lodepy-0.0.1.dist-info/LICENSE
lodepy-0.0.1.dist-info/METADATA
lodepy-0.0.1.dist-info/WHEEL
lodepy-0.0.1.dist-info/top_level.txt
lodepy-0.0.1.dist-info/RECORD
