Metadata-Version: 2.1
Name: lodepy
Version: 0.0.1
Summary: Fully python multi-node automation project
Author-email: Tyler Katchen <tkatchen7@gmail.com>
Classifier: Programming Language :: Python :: 3
Classifier: Operating System :: OS Independent
Requires-Python: >=3.7
License-File: LICENSE
